.gitattributes
.gitignore
Dockerfile
LICENSE
MANIFEST.in
README.md
setup.cfg
setup.py
tox.ini
.github/workflows/build_docs.yml
.github/workflows/main.yml
.github/workflows/publish-to-test-pypi.yml
docs/.buildinfo
docs/.nojekyll
docsource/Makefile
docsource/conf.py
docsource/config.rst
docsource/examples.rst
docsource/index.rst
docsource/install.rst
docsource/managing_metadata.rst
docsource/manuscript.rst
docsource/references.bib
docsource/running.rst
docsource/visualization.rst
docsource/analysis/SRP093386.sh
docsource/analysis/bahreini_tableS4_MCF7_D538GvsWT.csv
docsource/analysis/bahreini_tableS4_MCF7_Y537SvsWT.csv
docsource/analysis/config.json
docsource/analysis/contrasts.csv
docsource/analysis/de_plot.png
docsource/analysis/de_plot.svg
docsource/analysis/de_plot_nomask.png
docsource/analysis/de_plot_nomask.svg
docsource/analysis/fingerprint.txt
docsource/analysis/fingerprint_plot.png
docsource/analysis/fingerprint_plot.svg
docsource/analysis/manuscript_figures.ipynb
docsource/analysis/metadata.csv
docsource/analysis/metadata_exp.csv
docsource/analysis/qc_plot.png
docsource/analysis/qc_plot.svg
docsource/analysis/repeatmask_plot.png
docsource/analysis/repeatmask_plot.svg
docsource/analysis/volcano_plot.png
docsource/analysis/volcano_plot.svg
docsource/figures/de_plot.svg
docsource/figures/expression_example_1.png
docsource/figures/expression_example_2.png
docsource/figures/expression_example_3.png
docsource/figures/feature_table.csv
docsource/figures/pisces.graffle
docsource/figures/pisces.png
docsource/figures/pisces_index.png
docsource/figures/pisces_overview.png
docsource/figures/pisces_run.png
docsource/figures/pisces_submit.gif
docsource/figures/pisces_summarize.png
docsource/figures/qc_example_1.png
docsource/figures/qc_example_2.png
docsource/figures/qc_fingerprint.png
docsource/figures/qc_percent_ribomito.png
docsource/figures/qc_percent_transcript.png
docsource/figures/qc_plot.svg
docsource/figures/repeatmask_2dbin.png
novartis_pisces.egg-info/PKG-INFO
novartis_pisces.egg-info/SOURCES.txt
novartis_pisces.egg-info/dependency_links.txt
novartis_pisces.egg-info/entry_points.txt
novartis_pisces.egg-info/requires.txt
novartis_pisces.egg-info/top_level.txt
pisces/__init__.py
pisces/cli.py
