Metadata-Version: 2.1
Name: novartis-pisces
Version: 0.1.5.3
Summary: PISCES: pipeline for rapid transcript quantitation, genetic fingerprinting, and quality control assessment of RNAseq libraries
Home-page: https://github.com/Novartis/pisces
Author: Matthew Shirley
Author-email: matt_d.shirley@novartis.com
License: Apache
Platform: UNKNOWN
Classifier: Development Status :: 4 - Beta
Classifier: License :: OSI Approved :: Apache Software License
Classifier: Environment :: Console
Classifier: Intended Audience :: Science/Research
Classifier: Natural Language :: English
Classifier: Operating System :: Unix
Classifier: Programming Language :: Python :: 3.9
Classifier: Topic :: Scientific/Engineering :: Bio-Informatics
License-File: LICENSE
